ahpy/__init__.py
ahpy/_version.py
ahpy/ahpy.py
ahpy-2.1.dist-info/licenses/LICENSE
ahpy-2.1.dist-info/METADATA
ahpy-2.1.dist-info/WHEEL
ahpy-2.1.dist-info/top_level.txt
ahpy-2.1.dist-info/RECORD
