Metadata-Version: 2.4
Name: AHPy
Version: 2.1
Summary: A Python implementation of the Analytic Hierarchy Process
Author-email: Philip Griffith <philip.griffith@gmail.com>
License-Expression: MIT
Project-URL: Repository, https://github.com/PhilipGriffith/AHPy
Keywords: AHP,MCDM,MCDA
Classifier: Operating System :: OS Independent
Requires-Python: >=3.7
License-File: LICENSE
Requires-Dist: numpy
Requires-Dist: scipy
Dynamic: license-file
